
[
    {
        "Id":0,
        "Name":"Dynamite",
        "Description":"Blesse les ennemis pour 140% de l'attaque" ,
        "IsAoE":true ,
        "Type":4 ,
        "Health":140,
        "Animation":7,
        "Projectile":"dynamite",
        "Uses":5
    },
    {
        "Id":1,
        "Name":"Carotte Nom Nom",
        "Description":"Om nom nom" ,
        "IsAoE":false ,
        "Type":3 ,
        "Health":25,
        "Animation":3,
        "Projectile":"",
        "Uses":3
    },{
        "Id":2
        "Name":"Charge",
        "Description":"Blesse une cible ennemie pour 120% de l'attaque" ,
        "IsAoE":false ,
        "Type":4 ,
        "Health":120,
        "Animation":6,
        "Projectile":"",
        "Uses":100
    }

]
